{"content":[{"id":"6978a995","settings":{"gap":"no","stretch_section":"section-stretched","background_background":"classic","background_image":{"url":"https:\/\/xclean-demo.pbminfotech.com\/datasite\/wp-content\/uploads\/sites\/7\/2024\/09\/testimonial-bg-icon.png","id":4659,"size":"","alt":"testimonial-bg-icon","source":"library"},"background_position":"initial","background_ypos":{"unit":"px","size":500,"sizes":[]},"background_repeat":"no-repeat","padding":{"unit":"px","top":"100","right":"0","bottom":"100","left":"0","isLinked":false},"padding_tablet_extra":{"unit":"px","top":"80","right":"0","bottom":"80","left":"0","isLinked":false},"padding_tablet":{"unit":"px","top":"80","right":"0","bottom":"80","left":"0","isLinked":false},"padding_mobile":{"unit":"px","top":"60","right":"0","bottom":"60","left":"0","isLinked":false},"css_classes":"pbmit-bg-img-hide"},"elements":[{"id":"771bf0d0","settings":{"_column_size":100,"_inline_size":null,"padding":{"unit":"px","top":"0","right":"12","bottom":"0","left":"12","isLinked":false},"padding_laptop":{"unit":"px","top":"0","right":"30","bottom":"0","left":"30","isLinked":false}},"elements":[{"id":"4de080e9","settings":{"carousel-delay":"4000","carousel-speed":"3000","title":"Trusted by thousand of <br>people & companies.","style":"2","columns":"2","carousel-nav":"above","subtitle":"Testimonials","reverse_title":"yes","view-type":"carousel","title_animation":"2","gap":"40px"},"elements":[],"isInner":false,"widgetType":"pbmit_testimonial_element","elType":"widget"}],"isInner":false,"elType":"column"}],"isInner":false,"elType":"section"}],"page_settings":[],"version":"0.4","title":"Section08","type":"section"}